<index>
<tf id="113" file="etd2030/12/index.xml" title="Building institutional repositories in KLISC Member Institutions in Kenya: emerging challenges">0.001</tf>
<tf id="122" file="etd2030/18/index.xml" title="Examining access by country, language and areas of knowledge">0.001</tf>
<tf id="4" file="etd2031/2/index.xml" title="Do ETDs deter publishers? Does web availability count as prior publication?">0.001</tf>
<tf id="80" file="etd2011/14/index.xml" title="Enriching the VT ETD-db System with references">0.001</tf>
<tf id="32" file="etd2006/2/index.xml" title="Creative Commons.ca">0.001</tf>
<tf id="106" file="etd2030/14/index.xml" title="Enriching the VT ETD-db System with references">0.001</tf>
<tf id="130" file="etd2027/5/index.xml" title="Institutional repositories for open access: the Ghanaian experience">0.001</tf>
<tf id="96" file="etd2011/18/index.xml" title="Examining access by country, language and areas of knowledge">0.001</tf>
<tf id="103" file="etd2030/1/index.xml" title="Digitization efforts in the Federal University of Technology Owerri (Futo): successes, challenges, prospects">0.001</tf>
<tf id="148" file="etd2027/18/index.xml" title="Examining access by country, language and areas of knowledge">0.001</tf>
<tf id="16" file="etd2031/12/index.xml" title="Building institutional repositories in KLISC Member Institutions in Kenya: emerging challenges">0.001</tf>
<tf id="75" file="etd2011/2/index.xml" title="Do ETDs deter publishers? Does web availability count as prior publication?">0.001</tf>
<tf id="127" file="etd2027/2/index.xml" title="Do ETDs deter publishers? Does web availability count as prior publication?">0.001</tf>
<tf id="104" file="etd2030/5/index.xml" title="Institutional repositories for open access: the Ghanaian experience">0.001</tf>
<tf id="78" file="etd2011/5/index.xml" title="Institutional repositories for open access: the Ghanaian experience">0.001</tf>
<tf id="81" file="etd2011/16/index.xml" title="Data desiccation: facilitating long-term access, use, and reuse of ETDs">0.001</tf>
<tf id="129" file="etd2027/1/index.xml" title="Digitization efforts in the Federal University of Technology Owerri (Futo): successes, challenges, prospects">0.001</tf>
<tf id="139" file="etd2027/12/index.xml" title="Building institutional repositories in KLISC Member Institutions in Kenya: emerging challenges">0.001</tf>
<tf id="107" file="etd2030/16/index.xml" title="Data desiccation: facilitating long-term access, use, and reuse of ETDs">0.001</tf>
<tf id="48" file="etd2006/24/index.xml" title="Enhancing Digital Repository of Scholarly Publications at Indian Institute of Technology, Bombay">0.001</tf>
<tf id="132" file="etd2027/14/index.xml" title="Enriching the VT ETD-db System with references">0.001</tf>
<tf id="26" file="etd2006/13/index.xml" title="ETD's as pilot materials for long-term preservation efforts in kopal">0.001</tf>
<tf id="69" file="etd2006/10/index.xml" title="The Integration of Lithuanian ETD into the National Digital Library">0.001</tf>
<tf id="25" file="etd2031/18/index.xml" title="Examining access by country, language and areas of knowledge">0.001</tf>
<tf id="133" file="etd2027/16/index.xml" title="Data desiccation: facilitating long-term access, use, and reuse of ETDs">0.001</tf>
<tf id="6" file="etd2031/1/index.xml" title="Digitization efforts in the Federal University of Technology Owerri (Futo): successes, challenges, prospects">0.001</tf>
<tf id="77" file="etd2011/1/index.xml" title="Digitization efforts in the Federal University of Technology Owerri (Futo): successes, challenges, prospects">0.001</tf>
<tf id="101" file="etd2030/2/index.xml" title="Do ETDs deter publishers? Does web availability count as prior publication?">0.001</tf>
<tf id="35" file="etd2006/25/index.xml" title="Developing an E-Theses Collection in the CityU Institutional Repository">0.001</tf>
<tf id="7" file="etd2031/5/index.xml" title="Institutional repositories for open access: the Ghanaian experience">0.001</tf>
<tf id="87" file="etd2011/12/index.xml" title="Building institutional repositories in KLISC Member Institutions in Kenya: emerging challenges">0.001</tf>
<tf id="64" file="etd2006/31/index.xml" title="The Role of Penn State in Promoting Intellectual Property Rights Through ETDs publishing">0.002</tf>
<tf id="10" file="etd2031/16/index.xml" title="Data desiccation: facilitating long-term access, use, and reuse of ETDs">0.001</tf>
<tf id="9" file="etd2031/14/index.xml" title="Enriching the VT ETD-db System with references">0.001</tf>
</index>
