<index>
<tf id="123" file="etd2031/20/index.xml" title="Improving accessibility to collections of electronic theses and dissertations">0.001</tf>
<tf id="0" file="etd2011/20/index.xml" title="Improving accessibility to collections of electronic theses and dissertations">0.001</tf>
<tf id="26" file="etd2027/20/index.xml" title="Improving accessibility to collections of electronic theses and dissertations">0.001</tf>
<tf id="79" file="etd2006/31/index.xml" title="The Role of Penn State in Promoting Intellectual Property Rights Through ETDs publishing">0.001</tf>
<tf id="80" file="etd2006/30/index.xml" title="Developing legal protocols and practices for managing copyright in electronic theses">0.003</tf>
<tf id="3" file="etd2011/9/index.xml" title="First a trial balloon, now an established workflow: collecting electronic thesis at the German National Library">0.001</tf>
<tf id="126" file="etd2031/9/index.xml" title="First a trial balloon, now an established workflow: collecting electronic thesis at the German National Library">0.001</tf>
<tf id="100" file="etd2030/9/index.xml" title="First a trial balloon, now an established workflow: collecting electronic thesis at the German National Library">0.001</tf>
<tf id="97" file="etd2030/20/index.xml" title="Improving accessibility to collections of electronic theses and dissertations">0.001</tf>
<tf id="29" file="etd2027/9/index.xml" title="First a trial balloon, now an established workflow: collecting electronic thesis at the German National Library">0.001</tf>
</index>
