<index>
<tf id="109" file="etd2006/11/index.xml" title="Digital Preservation for ETDs">0.001</tf>
<tf id="1" file="etd2011/19/index.xml" title="Where Sharing Should Not Go: An Environmental Scan of Originality Assurance Awareness and Efforts to Discourage or Prevent Plagiarism">0.001</tf>
<tf id="65" file="etd2027/12/index.xml" title="Building institutional repositories in KLISC Member Institutions in Kenya: emerging challenges">0.001</tf>
<tf id="79" file="etd2030/19/index.xml" title="Where Sharing Should Not Go: An Environmental Scan of Originality Assurance Awareness and Efforts to Discourage or Prevent Plagiarism">0.001</tf>
<tf id="53" file="etd2027/19/index.xml" title="Where Sharing Should Not Go: An Environmental Scan of Originality Assurance Awareness and Efforts to Discourage or Prevent Plagiarism">0.001</tf>
<tf id="13" file="etd2011/12/index.xml" title="Building institutional repositories in KLISC Member Institutions in Kenya: emerging challenges">0.001</tf>
<tf id="39" file="etd2031/12/index.xml" title="Building institutional repositories in KLISC Member Institutions in Kenya: emerging challenges">0.001</tf>
<tf id="91" file="etd2030/12/index.xml" title="Building institutional repositories in KLISC Member Institutions in Kenya: emerging challenges">0.001</tf>
<tf id="27" file="etd2031/19/index.xml" title="Where Sharing Should Not Go: An Environmental Scan of Originality Assurance Awareness and Efforts to Discourage or Prevent Plagiarism">0.001</tf>
</index>
