<index>
<tf id="30" file="etd2031/17/index.xml" title="Two South African institutional repositories: a comparative overview">0.001</tf>
<tf id="4" file="etd2011/17/index.xml" title="Two South African institutional repositories: a comparative overview">0.001</tf>
<tf id="56" file="etd2027/17/index.xml" title="Two South African institutional repositories: a comparative overview">0.001</tf>
<tf id="114" file="etd2006/18/index.xml" title="An Overview of Theses Canada and ETD Initiatives at Library and Archives Canada">0.001</tf>
<tf id="82" file="etd2030/17/index.xml" title="Two South African institutional repositories: a comparative overview">0.001</tf>
</index>
