<index>
<tf id="41" file="etd2031/24/index.xml" title="Digitization of theses and dissertations: status quo India">0.001</tf>
<tf id="112" file="etd2011/24/index.xml" title="Digitization of theses and dissertations: status quo India">0.001</tf>
<tf id="138" file="etd2027/24/index.xml" title="Digitization of theses and dissertations: status quo India">0.001</tf>
<tf id="63" file="etd2006/25/index.xml" title="Developing an E-Theses Collection in the CityU Institutional Repository">0.001</tf>
<tf id="73" file="etd2006/19/index.xml" title="A workflow system for ETDs. A supportive feature in the electronic publishing chain">0.001</tf>
<tf id="15" file="etd2030/24/index.xml" title="Digitization of theses and dissertations: status quo India">0.001</tf>
<tf id="57" file="etd2006/40/index.xml" title="EThOS (Electronic Theses Online Service) - a national UK project">0.001</tf>
</index>
