<index>
<tf id="26" file="etd2031/17/index.xml" title="Two South African institutional repositories: a comparative overview">0.001</tf>
<tf id="42" file="etd2031/5/index.xml" title="Institutional repositories for open access: the Ghanaian experience">0.001</tf>
<tf id="123" file="etd2027/17/index.xml" title="Two South African institutional repositories: a comparative overview">0.001</tf>
<tf id="86" file="etd2006/18/index.xml" title="An Overview of Theses Canada and ETD Initiatives at Library and Archives Canada">0.001</tf>
<tf id="112" file="etd2011/24/index.xml" title="Digitization of theses and dissertations: status quo India">0.001</tf>
<tf id="41" file="etd2031/24/index.xml" title="Digitization of theses and dissertations: status quo India">0.001</tf>
<tf id="111" file="etd2011/13/index.xml" title="Assessing awareness of repositories and the Open Access Movement among ETD Faculty Advisors">0.002</tf>
<tf id="40" file="etd2031/13/index.xml" title="Assessing awareness of repositories and the Open Access Movement among ETD Faculty Advisors">0.002</tf>
<tf id="139" file="etd2027/5/index.xml" title="Institutional repositories for open access: the Ghanaian experience">0.001</tf>
<tf id="138" file="etd2027/24/index.xml" title="Digitization of theses and dissertations: status quo India">0.001</tf>
<tf id="113" file="etd2011/5/index.xml" title="Institutional repositories for open access: the Ghanaian experience">0.001</tf>
<tf id="80" file="etd2006/5/index.xml" title="Open Access for ETDs">0.019</tf>
<tf id="16" file="etd2030/5/index.xml" title="Institutional repositories for open access: the Ghanaian experience">0.001</tf>
<tf id="97" file="etd2011/17/index.xml" title="Two South African institutional repositories: a comparative overview">0.001</tf>
<tf id="84" file="etd2006/22/index.xml" title="The Institutional Repository at West Virginia University Libraries: Resources for Effective Promotion">0.001</tf>
<tf id="137" file="etd2027/13/index.xml" title="Assessing awareness of repositories and the Open Access Movement among ETD Faculty Advisors">0.002</tf>
<tf id="15" file="etd2030/24/index.xml" title="Digitization of theses and dissertations: status quo India">0.001</tf>
<tf id="0" file="etd2030/17/index.xml" title="Two South African institutional repositories: a comparative overview">0.001</tf>
<tf id="14" file="etd2030/13/index.xml" title="Assessing awareness of repositories and the Open Access Movement among ETD Faculty Advisors">0.002</tf>
</index>
