<index>
<tf id="67" file="etd2006/15/index.xml" title="Supply and Demand Analysis in NDLTD Based on Patron Specialty Survey and Contents Statistics">0.001</tf>
<tf id="138" file="etd2027/24/index.xml" title="Digitization of theses and dissertations: status quo India">0.001</tf>
<tf id="15" file="etd2030/24/index.xml" title="Digitization of theses and dissertations: status quo India">0.001</tf>
<tf id="112" file="etd2011/24/index.xml" title="Digitization of theses and dissertations: status quo India">0.001</tf>
<tf id="41" file="etd2031/24/index.xml" title="Digitization of theses and dissertations: status quo India">0.001</tf>
</index>
